Metadata-Version: 2.1
Name: stuffr
Version: 1.0.0
Summary: Stuff from R implemented in Python
Home-page: UNKNOWN
Author: Juha Vierinen, Vetle Hofsøy-Woie
Author-email: juha-pekka.vierinen@uit.no
License: UNKNOWN
Platform: UNKNOWN
Classifier: Development Status :: 4 - Beta
Classifier: Intended Audience :: Science/Research
Classifier: Natural Language :: English
Classifier: Programming Language :: Python :: 3
Requires-Python: >=3.6
